py92/__init__.py
py92/cn_schools.csv
py92/config.py
py92/py92utils.py
py92/qs2024.csv
tests/__init__.py
tests/test_module.py
py92-1.0.3.dist-info/LICENSE
py92-1.0.3.dist-info/METADATA
py92-1.0.3.dist-info/WHEEL
py92-1.0.3.dist-info/top_level.txt
py92-1.0.3.dist-info/RECORD
