Metadata-Version: 2.1
Name: py92
Version: 1.0.3
Summary: Python Packages for Labeling(985/211/双一流/本科) Schools in China
Home-page: https://github.com/stanleysun233/py92
Author: Stanley SUN
Author-email: stanleysun233@163.com
Classifier: Programming Language :: Python :: 3
Classifier: License :: OSI Approved :: MIT License
Classifier: Operating System :: OS Independent
Requires-Python: >=3.5
License-File: LICENSE
Requires-Dist: pandas
